[
  {
    "text": "Java",
    "collapsible": true,
    "collapsed": false,
    "items": [
      {
        "text": "Java 学习路线-前端功利性",
        "link": "/posts/Java/Java 学习路线-前端功利性"
      }
    ]
  },
  {
    "text": "JavaScriptCore",
    "collapsible": true,
    "collapsed": false,
    "items": [
      { "text": "IIFE", "link": "/posts/JavaScriptCore/IIFE" },
      {
        "text": "JavaScript中运算符优先级",
        "link": "/posts/JavaScriptCore/JavaScript中运算符优先级"
      },
      {
        "text": "generator和iterator",
        "link": "/posts/JavaScriptCore/generator和iterator"
      },
      {
        "text": "js让人诟病的这些feature",
        "link": "/posts/JavaScriptCore/js让人诟病的这些feature"
      },
      { "text": "parseInt 1", "link": "/posts/JavaScriptCore/parseInt 1" },
      { "text": "parseInt", "link": "/posts/JavaScriptCore/parseInt" },
      { "text": "prototype", "link": "/posts/JavaScriptCore/prototype" },
      {
        "text": "作用域（链）、执行上下文、闭包",
        "link": "/posts/JavaScriptCore/作用域（链）、执行上下文、闭包"
      },
      { "text": "再次理解闭包", "link": "/posts/JavaScriptCore/再次理解闭包" },
      {
        "text": "块级作用域与嵌套、let、暂时性死区",
        "link": "/posts/JavaScriptCore/块级作用域与嵌套、let、暂时性死区"
      },
      {
        "text": "对象的属性描述符",
        "link": "/posts/JavaScriptCore/对象的属性描述符"
      },
      {
        "text": "对象的访问器属性",
        "link": "/posts/JavaScriptCore/对象的访问器属性"
      },
      { "text": "对象继承", "link": "/posts/JavaScriptCore/对象继承" },
      { "text": "数组API", "link": "/posts/JavaScriptCore/数组API" },
      { "text": "正则基础", "link": "/posts/JavaScriptCore/正则基础" },
      { "text": "立即执行函数", "link": "/posts/JavaScriptCore/立即执行函数" },
      { "text": "类数组", "link": "/posts/JavaScriptCore/类数组" },
      {
        "text": "让 a == 1 && a == 2 && a == 3 成立",
        "link": "/posts/JavaScriptCore/让 a == 1 && a == 2 && a == 3 成立"
      },
      { "text": "转义符", "link": "/posts/JavaScriptCore/转义符" },
      {
        "text": "运算符的优先级",
        "link": "/posts/JavaScriptCore/运算符的优先级"
      },
      { "text": "错误信息", "link": "/posts/JavaScriptCore/错误信息" },
      { "text": "闭包", "link": "/posts/JavaScriptCore/闭包" },
      { "text": "隐式转化问题", "link": "/posts/JavaScriptCore/隐式转化问题" }
    ]
  },
  {
    "text": "Vue",
    "collapsible": true,
    "collapsed": false,
    "items": [{ "text": "vapor", "link": "/posts/Vue/vapor" }]
  },
  {
    "text": "最佳实践",
    "collapsible": true,
    "collapsed": false,
    "items": [
      { "text": "", "link": "/posts/最佳实践/" },
      { "text": "CodeReview礼仪", "link": "/posts/最佳实践/CodeReview礼仪" },
      {
        "text": "Code评审模板和礼仪",
        "link": "/posts/最佳实践/Code评审模板和礼仪"
      },
      {
        "text": "React中如何分组件",
        "link": "/posts/最佳实践/React中如何分组件"
      },
      {
        "text": "TS入门教程学习总结",
        "link": "/posts/最佳实践/TS入门教程学习总结"
      },
      { "text": "VsCode中使用vim", "link": "/posts/最佳实践/VsCode中使用vim" },
      {
        "text": "\\使用composition api实践经验",
        "link": "/posts/最佳实践/\\使用composition api实践经验"
      },
      {
        "text": "vue的业务开发如何进行组件的拆分",
        "link": "/posts/最佳实践/vue的业务开发如何进行组件的拆分"
      },
      { "text": "《重构》导读", "link": "/posts/最佳实践/《重构》导读" },
      {
        "text": "产品经理不靠谱怎么办_",
        "link": "/posts/最佳实践/产品经理不靠谱怎么办_"
      },
      {
        "text": "代码审查常见问题",
        "link": "/posts/最佳实践/代码审查常见问题"
      },
      { "text": "前端已死_", "link": "/posts/最佳实践/前端已死_" },
      { "text": "如何设计组件？", "link": "/posts/最佳实践/如何设计组件？" },
      { "text": "如何阅读源码", "link": "/posts/最佳实践/如何阅读源码" },
      {
        "text": "富文本无法渲染多个空格",
        "link": "/posts/最佳实践/富文本无法渲染多个空格"
      }
    ]
  }
]
